pylint_airflow/__init__.py
pylint_airflow/__pkginfo__.py
pylint_airflow/checkers/__init__.py
pylint_airflow/checkers/dag.py
pylint_airflow/checkers/operator.py
pylint_airflow/checkers/xcom.py
pylint_airflow-0.1.0a1.dist-info/LICENSE
pylint_airflow-0.1.0a1.dist-info/METADATA
pylint_airflow-0.1.0a1.dist-info/WHEEL
pylint_airflow-0.1.0a1.dist-info/top_level.txt
pylint_airflow-0.1.0a1.dist-info/RECORD
