Metadata-Version: 2.1
Name: pylint-airflow
Version: 0.1.0a1
Summary: A Pylint plugin to lint Apache Airflow code.
Home-page: https://github.com/BasPH/pylint-airflow
License: UNKNOWN
Keywords: pylint,airflow,plugin
Platform: UNKNOWN
Classifier: Development Status :: 3 - Alpha
Classifier: Intended Audience :: Developers
Classifier: License :: OSI Approved :: MIT License
Classifier: Natural Language :: English
Classifier: Programming Language :: Python :: 3
Classifier: Programming Language :: Python :: 3.6
Classifier: Programming Language :: Python :: 3.7
Requires-Dist: pylint
